drf_static_router/__init__.py
drf_static_router/routers.py
drf_static_router/tests/__init__.py
drf_static_router-0.0.1.dist-info/LICENSE
drf_static_router-0.0.1.dist-info/WHEEL
drf_static_router-0.0.1.dist-info/METADATA
drf_static_router-0.0.1.dist-info/RECORD
